cleanser/__init__.py
cleanser/core/__init__.py
cleanser/core/generic.py
cleanser/core/reddit.py
cleanser-0.2.3.dist-info/LICENSE
cleanser-0.2.3.dist-info/WHEEL
cleanser-0.2.3.dist-info/METADATA
cleanser-0.2.3.dist-info/RECORD
