Metadata-Version: 2.1
Name: cleanser
Version: 0.2.3
Summary: Tools for cleaning text.
Home-page: https://github.com/mholtzscher/cleanser
License: MIT
Keywords: cleansing,data
Author: Michael Holtzscher
Author-email: mholtz@protonmail.com
Requires-Python: >=3.6,<4.0
Classifier: License :: OSI Approved :: MIT License
Classifier: Programming Language :: Python :: 3
Classifier: Programming Language :: Python :: 3.6
Classifier: Programming Language :: Python :: 3.7
Project-URL: Repository, https://github.com/mholtzscher/cleanser
